piscord/API_Elements.py
piscord/Errors.py
piscord/Events.py
piscord/Gateway.py
piscord/OAuth.py
piscord/Permission.py
piscord/Piscord.py
piscord/Voice.py
piscord/__init__.py
piscord/modules/Handler.py
piscord-1.5.0.post1.dist-info/LICENSE
piscord-1.5.0.post1.dist-info/METADATA
piscord-1.5.0.post1.dist-info/WHEEL
piscord-1.5.0.post1.dist-info/top_level.txt
piscord-1.5.0.post1.dist-info/RECORD
