Metadata-Version: 2.1
Name: piscord
Version: 1.5.0.post1
Summary: Piscord is a python framework to communicate with the Discord api.
Home-page: https://github.com/Astremy/Piscord
Author: Astremy
License: LICENSE
Platform: UNKNOWN
Classifier: Programming Language :: Python :: 3
Classifier: License :: OSI Approved :: MIT License
Classifier: Operating System :: OS Independent
Requires-Python: >=3.6
Requires-Dist: aiohttp (==3.6.2)
Requires-Dist: websockets (==8.1)
